{
    "name": "I Miei Sport Live",
    "author": "AutoUpdate",
    "groups": [
        {
            "name": "Eventi Live",
            "stations": [
                {
                    "name": "ST | Bayer Leverkusenin 2h 8mArsenal",
                    "url": "https://www.streameast24.com/live/important-games/match/bayer-leverkusen-vs-arsenal/69b1210162673af5aa15074a",
                    "image": "https://www.streameast24.com/favicon.ico",
                    "isHost": true
                },
                {
                    "name": "ST | PSGin 4h 23mChelsea",
                    "url": "https://www.streameast24.com/live/important-games/match/psg-vs-chelsea/69b1210162673af5aa15074b",
                    "image": "https://www.streameast24.com/favicon.ico",
                    "isHost": true
                },
                {
                    "name": "ST | Real Madridin 4h 23mManchester City",
                    "url": "https://www.streameast24.com/live/important-games/match/real-madrid-vs-manchester-city/69b1210162673af5aa15074c",
                    "image": "https://www.streameast24.com/favicon.ico",
                    "isHost": true
                },
                {
                    "name": "ST | Arsenal Livein 2h 8mBayer Leverkusen",
                    "url": "https://www.streameast24.com/live/soccer/match/arsenal-live-vs-bayer-leverkusen/69b14b0eef29282e0f1453f2",
                    "image": "https://www.streameast24.com/favicon.ico",
                    "isHost": true
                },
                {
                    "name": "ST | Chelsea Livein 4h 23mPSG Live",
                    "url": "https://www.streameast24.com/live/soccer/match/chelsea-live-vs-psg-live/69b14b48ef29282e0f145410",
                    "image": "https://www.streameast24.com/favicon.ico",
                    "isHost": true
                },
                {
                    "name": "ST | Man City Livein 4h 23mReal Madrid Live",
                    "url": "https://www.streameast24.com/live/soccer/match/man-city-live-vs-real-madrid-live/69b14b90ef29282e0f145425",
                    "image": "https://www.streameast24.com/favicon.ico",
                    "isHost": true
                },
                {
                    "name": "ST | Bodo  Glimtin 4h 23mSporting CP",
                    "url": "https://www.streameast24.com/live/uefa-champions-league/match/bodo-glimt-vs-sporting-cp/69b1210162673af5aa15074d",
                    "image": "https://www.streameast24.com/favicon.ico",
                    "isHost": true
                },
                {
                    "name": "ST | BNP Paribas Nordic Openin 9h 23mTennis",
                    "url": "https://www.streameast24.com/live/tennis/match/bnp-paribas-nordic-open-vs-tennis/69562d0662673af5aa14f984",
                    "image": "https://www.streameast24.com/favicon.ico",
                    "isHost": true
                },
                {
                    "name": "ST | Singapore U19Live nowMaldives U20",
                    "url": "https://www.streameast24.com/live/international-friendlies/match/singapore-u19-vs-maldives-u20/69b1210162673af5aa15074e",
                    "image": "https://www.streameast24.com/favicon.ico",
                    "isHost": true
                },
                {
                    "name": "ST | AFC Wimbledonin 4h 8mBlackpool",
                    "url": "https://www.streameast24.com/live/england-league-one/match/afc-wimbledon-vs-blackpool/69b1210162673af5aa150750",
                    "image": "https://www.streameast24.com/favicon.ico",
                    "isHost": true
                },
                {
                    "name": "ST | Port Valein 4h 8mBradford City",
                    "url": "https://www.streameast24.com/live/england-league-one/match/port-vale-vs-bradford-city/69b1210162673af5aa15074f",
                    "image": "https://www.streameast24.com/favicon.ico",
                    "isHost": true
                },
                {
                    "name": "ST | Birmingham Cityin 4h 8mQueens Park Rangers",
                    "url": "https://www.streameast24.com/live/england-championship/match/birmingham-city-vs-queens-park-rangers/69b1210162673af5aa150751",
                    "image": "https://www.streameast24.com/favicon.ico",
                    "isHost": true
                },
                {
                    "name": "ST | Middlesbroughin 4h 8mCharlton Athletic",
                    "url": "https://www.streameast24.com/live/england-championship/match/middlesbrough-vs-charlton-athletic/69b1210162673af5aa150752",
                    "image": "https://www.streameast24.com/favicon.ico",
                    "isHost": true
                },
                {
                    "name": "ST | Norwich Cityin 4h 8mSheffield United",
                    "url": "https://www.streameast24.com/live/england-championship/match/norwich-city-vs-sheffield-united/69b1210162673af5aa150755",
                    "image": "https://www.streameast24.com/favicon.ico",
                    "isHost": true
                },
                {
                    "name": "ST | Oxford Unitedin 4h 8mBlackburn Rovers",
                    "url": "https://www.streameast24.com/live/england-championship/match/oxford-united-vs-blackburn-rovers/69b1210162673af5aa150753",
                    "image": "https://www.streameast24.com/favicon.ico",
                    "isHost": true
                },
                {
                    "name": "ST | West Bromwich Albionin 4h 8mSouthampton",
                    "url": "https://www.streameast24.com/live/england-championship/match/west-bromwich-albion-vs-southampton/69b1210162673af5aa150754",
                    "image": "https://www.streameast24.com/favicon.ico",
                    "isHost": true
                },
                {
                    "name": "ST | Coventry Cityin 4h 23mPreston North End",
                    "url": "https://www.streameast24.com/live/england-championship/match/coventry-city-vs-preston-north-end/69b1210162673af5aa150756",
                    "image": "https://www.streameast24.com/favicon.ico",
                    "isHost": true
                },
                {
                    "name": "ST | Paris FCLive nowStrasbourg",
                    "url": "https://www.streameast24.com/live/division-1-feminine/match/paris-fc-vs-strasbourg/69b1210162673af5aa150757",
                    "image": "https://www.streameast24.com/favicon.ico",
                    "isHost": true
                },
                {
                    "name": "ST | PSGLive nowOlympique Marseille",
                    "url": "https://www.streameast24.com/live/division-1-feminine/match/psg-vs-olympique-marseille/69b1210162673af5aa15075b",
                    "image": "https://www.streameast24.com/favicon.ico",
                    "isHost": true
                },
                {
                    "name": "ST | Dijonin 2h 23mSaint Etienne",
                    "url": "https://www.streameast24.com/live/division-1-feminine/match/dijon-vs-saint-etienne/69b1210162673af5aa150759",
                    "image": "https://www.streameast24.com/favicon.ico",
                    "isHost": true
                },
                {
                    "name": "ST | Lensin 2h 23mMontpellier",
                    "url": "https://www.streameast24.com/live/division-1-feminine/match/lens-vs-montpellier/69b1210162673af5aa15075a",
                    "image": "https://www.streameast24.com/favicon.ico",
                    "isHost": true
                },
                {
                    "name": "ST | Nantesin 2h 23mFleury 91",
                    "url": "https://www.streameast24.com/live/division-1-feminine/match/nantes-vs-fleury-91/69b1210162673af5aa150758",
                    "image": "https://www.streameast24.com/favicon.ico",
                    "isHost": true
                },
                {
                    "name": "ST | Orlando Magicin 7h 34mCleveland Cavaliers",
                    "url": "https://www.streameast24.com/live/nba/match/orlando-magic-vs-cleveland-cavaliers/6933ca9b62673af5aa14f449",
                    "image": "https://www.streameast24.com/favicon.ico",
                    "isHost": true
                },
                {
                    "name": "ST | New Orleans Pelicansin 7h 34mToronto Raptors",
                    "url": "https://www.streameast24.com/live/nba/match/new-orleans-pelicans-vs-toronto-raptors/6933ca9b62673af5aa14f44a",
                    "image": "https://www.streameast24.com/favicon.ico",
                    "isHost": true
                },
                {
                    "name": "ST | Utah Jazzin 7h 34mNew York Knicks",
                    "url": "https://www.streameast24.com/live/nba/match/utah-jazz-vs-new-york-knicks/6933ca9b62673af5aa14f44b",
                    "image": "https://www.streameast24.com/favicon.ico",
                    "isHost": true
                },
                {
                    "name": "ST | Denver Nuggetsin 7h 34mHouston Rockets",
                    "url": "https://www.streameast24.com/live/nba/match/denver-nuggets-vs-houston-rockets/6933ca9b62673af5aa14f44c",
                    "image": "https://www.streameast24.com/favicon.ico",
                    "isHost": true
                },
                {
                    "name": "ST | Sacramento Kingsin 7h 34mCharlotte Hornets",
                    "url": "https://www.streameast24.com/live/nba/match/sacramento-kings-vs-charlotte-hornets/6933ca9b62673af5aa14f44d",
                    "image": "https://www.streameast24.com/favicon.ico",
                    "isHost": true
                },
                {
                    "name": "ST | LA Clippersin 7h 34mMinnesota Timberwolves",
                    "url": "https://www.streameast24.com/live/nba/match/la-clippers-vs-minnesota-timberwolves/6933ca9b62673af5aa14f44e",
                    "image": "https://www.streameast24.com/favicon.ico",
                    "isHost": true
                },
                {
                    "name": "ST | Baltimore Oriolesin 1h 28mPittsburgh Pirates",
                    "url": "https://www.streameast24.com/live/mlb/match/baltimore-orioles-vs-pittsburgh-pirates/69b1210862673af5aa150763",
                    "image": "https://www.streameast24.com/favicon.ico",
                    "isHost": true
                },
                {
                    "name": "ST | Washington Nationalsin 1h 28mSt. Louis Cardinals",
                    "url": "https://www.streameast24.com/live/mlb/match/washington-nationals-vs-st-louis-cardinals/69b1210762673af5aa15075f",
                    "image": "https://www.streameast24.com/favicon.ico",
                    "isHost": true
                },
                {
                    "name": "ST | Minnesota Twinsin 1h 28mDetroit Tigers",
                    "url": "https://www.streameast24.com/live/mlb/match/minnesota-twins-vs-detroit-tigers/69b1210862673af5aa150768",
                    "image": "https://www.streameast24.com/favicon.ico",
                    "isHost": true
                },
                {
                    "name": "ST | Atlanta Bravesin 1h 28mTampa Bay Rays",
                    "url": "https://www.streameast24.com/live/mlb/match/atlanta-braves-vs-tampa-bay-rays/69b1210862673af5aa150764",
                    "image": "https://www.streameast24.com/favicon.ico",
                    "isHost": true
                },
                {
                    "name": "ST | Miami Marlinsin 1h 33mHouston Astros",
                    "url": "https://www.streameast24.com/live/mlb/match/miami-marlins-vs-houston-astros/69b1210862673af5aa150765",
                    "image": "https://www.streameast24.com/favicon.ico",
                    "isHost": true
                },
                {
                    "name": "ST | Cincinnati Redsin 4h 28mMilwaukee Brewers",
                    "url": "https://www.streameast24.com/live/mlb/match/cincinnati-reds-vs-milwaukee-brewers/69b1210862673af5aa150767",
                    "image": "https://www.streameast24.com/favicon.ico",
                    "isHost": true
                },
                {
                    "name": "ST | Chicago White Soxin 4h 28mLos Angeles Angels",
                    "url": "https://www.streameast24.com/live/mlb/match/chicago-white-sox-vs-los-angeles-angels/69b1210762673af5aa150760",
                    "image": "https://www.streameast24.com/favicon.ico",
                    "isHost": true
                },
                {
                    "name": "ST | Kansas City Royalsin 4h 28mSan Francisco Giants",
                    "url": "https://www.streameast24.com/live/mlb/match/kansas-city-royals-vs-san-francisco-giants/69b1210862673af5aa150761",
                    "image": "https://www.streameast24.com/favicon.ico",
                    "isHost": true
                },
                {
                    "name": "ST | Chicago Cubsin 4h 28mKansas City Royals",
                    "url": "https://www.streameast24.com/live/mlb/match/chicago-cubs-vs-kansas-city-royals/69b1210862673af5aa15076a",
                    "image": "https://www.streameast24.com/favicon.ico",
                    "isHost": true
                },
                {
                    "name": "ST | Arizona Diamondbacksin 4h 33mOakland Athletics",
                    "url": "https://www.streameast24.com/live/mlb/match/arizona-diamondbacks-vs-oakland-athletics/69b1210862673af5aa150769",
                    "image": "https://www.streameast24.com/favicon.ico",
                    "isHost": true
                },
                {
                    "name": "ST | Seattle Marinersin 4h 33mColorado Rockies",
                    "url": "https://www.streameast24.com/live/mlb/match/seattle-mariners-vs-colorado-rockies/69b1210862673af5aa150766",
                    "image": "https://www.streameast24.com/favicon.ico",
                    "isHost": true
                },
                {
                    "name": "ST | New York Yankeesin 6h 58mToronto Blue Jays",
                    "url": "https://www.streameast24.com/live/mlb/match/new-york-yankees-vs-toronto-blue-jays/69b1210862673af5aa150762",
                    "image": "https://www.streameast24.com/favicon.ico",
                    "isHost": true
                },
                {
                    "name": "ST | Senatorsin 7h 53mCanadeins",
                    "url": "https://www.streameast24.com/live/nhl/match/senators-vs-canadeins/69b1210962673af5aa15076b",
                    "image": "https://www.streameast24.com/favicon.ico",
                    "isHost": true
                },
                {
                    "name": "ST | Flyersin 7h 53mCapitals",
                    "url": "https://www.streameast24.com/live/nhl/match/flyers-vs-capitals/69b1210962673af5aa15076c",
                    "image": "https://www.streameast24.com/favicon.ico",
                    "isHost": true
                },
                {
                    "name": "TV | ACC Network",
                    "url": "https://thetvapp.to/tv/acc-network-live-stream/",
                    "image": "https://the-tv.app/favicon.ico",
                    "isHost": true
                },
                {
                    "name": "TV | American Heroes Channel",
                    "url": "https://thetvapp.to/tv/american-heroes-channel-live-stream/",
                    "image": "https://the-tv.app/favicon.ico",
                    "isHost": true
                },
                {
                    "name": "TV | Animal Planet",
                    "url": "https://thetvapp.to/tv/animal-planet-live-stream/",
                    "image": "https://the-tv.app/favicon.ico",
                    "isHost": true
                },
                {
                    "name": "TV | BBC America",
                    "url": "https://thetvapp.to/tv/bbc-america-live-stream/",
                    "image": "https://the-tv.app/favicon.ico",
                    "isHost": true
                },
                {
                    "name": "TV | BBC World News HD",
                    "url": "https://thetvapp.to/tv/bbc-world-news-hd-live-stream/",
                    "image": "https://the-tv.app/favicon.ico",
                    "isHost": true
                },
                {
                    "name": "TV | BET Her",
                    "url": "https://thetvapp.to/tv/bet-her-live-stream/",
                    "image": "https://the-tv.app/favicon.ico",
                    "isHost": true
                },
                {
                    "name": "TV | Big Ten Network",
                    "url": "https://thetvapp.to/tv/big-ten-network-live-stream/",
                    "image": "https://the-tv.app/favicon.ico",
                    "isHost": true
                },
                {
                    "name": "TV | Bloomberg TV",
                    "url": "https://thetvapp.to/tv/bloomberg-tv-live-stream/",
                    "image": "https://the-tv.app/favicon.ico",
                    "isHost": true
                },
                {
                    "name": "TV | Boomerang",
                    "url": "https://thetvapp.to/tv/boomerang-live-stream/",
                    "image": "https://the-tv.app/favicon.ico",
                    "isHost": true
                },
                {
                    "name": "TV | Bravo",
                    "url": "https://thetvapp.to/tv/bravo-live-stream/",
                    "image": "https://the-tv.app/favicon.ico",
                    "isHost": true
                },
                {
                    "name": "TV | Cartoon Network",
                    "url": "https://thetvapp.to/tv/cartoon-network-live-stream/",
                    "image": "https://the-tv.app/favicon.ico",
                    "isHost": true
                },
                {
                    "name": "TV | CBS Sports Network",
                    "url": "https://thetvapp.to/tv/cbs-sports-network-live-stream/",
                    "image": "https://the-tv.app/favicon.ico",
                    "isHost": true
                },
                {
                    "name": "TV | Cinemax",
                    "url": "https://thetvapp.to/tv/cinemax-live-stream/",
                    "image": "https://the-tv.app/favicon.ico",
                    "isHost": true
                },
                {
                    "name": "TV | CNBC",
                    "url": "https://thetvapp.to/tv/cnbc-live-stream/",
                    "image": "https://the-tv.app/favicon.ico",
                    "isHost": true
                },
                {
                    "name": "TV | Comedy Central",
                    "url": "https://thetvapp.to/tv/comedy-central-live-stream/",
                    "image": "https://the-tv.app/favicon.ico",
                    "isHost": true
                },
                {
                    "name": "TV | Cooking Channel",
                    "url": "https://thetvapp.to/tv/cooking-channel-live-stream/",
                    "image": "https://the-tv.app/favicon.ico",
                    "isHost": true
                },
                {
                    "name": "TV | Crime & Investigation HD",
                    "url": "https://thetvapp.to/tv/crime-investigation-hd-live-stream/",
                    "image": "https://the-tv.app/favicon.ico",
                    "isHost": true
                },
                {
                    "name": "TV | CSPAN",
                    "url": "https://thetvapp.to/tv/cspan-live-stream/",
                    "image": "https://the-tv.app/favicon.ico",
                    "isHost": true
                },
                {
                    "name": "TV | CSPAN 2",
                    "url": "https://thetvapp.to/tv/cspan-2-live-stream/",
                    "image": "https://the-tv.app/favicon.ico",
                    "isHost": true
                },
                {
                    "name": "TV | Destination America",
                    "url": "https://thetvapp.to/tv/destination-america-live-stream/",
                    "image": "https://the-tv.app/favicon.ico",
                    "isHost": true
                },
                {
                    "name": "TV | Discovery",
                    "url": "https://thetvapp.to/tv/discovery-live-stream/",
                    "image": "https://the-tv.app/favicon.ico",
                    "isHost": true
                },
                {
                    "name": "TV | Discovery Family Channel",
                    "url": "https://thetvapp.to/tv/discovery-family-channel-live-stream/",
                    "image": "https://the-tv.app/favicon.ico",
                    "isHost": true
                },
                {
                    "name": "TV | Discovery Life",
                    "url": "https://thetvapp.to/tv/discovery-life-live-stream/",
                    "image": "https://the-tv.app/favicon.ico",
                    "isHost": true
                },
                {
                    "name": "TV | Disney Channel (East)",
                    "url": "https://thetvapp.to/tv/disney-channel-east-live-stream/",
                    "image": "https://the-tv.app/favicon.ico",
                    "isHost": true
                },
                {
                    "name": "TV | Disney Junior",
                    "url": "https://thetvapp.to/tv/disney-junior-live-stream/",
                    "image": "https://the-tv.app/favicon.ico",
                    "isHost": true
                },
                {
                    "name": "TV | Disney XD",
                    "url": "https://thetvapp.to/tv/disney-xd-live-stream/",
                    "image": "https://the-tv.app/favicon.ico",
                    "isHost": true
                },
                {
                    "name": "TV | ESPN",
                    "url": "https://thetvapp.to/tv/espn-live-stream/",
                    "image": "https://the-tv.app/favicon.ico",
                    "isHost": true
                },
                {
                    "name": "TV | ESPN2",
                    "url": "https://thetvapp.to/tv/espn2-live-stream/",
                    "image": "https://the-tv.app/favicon.ico",
                    "isHost": true
                },
                {
                    "name": "TV | ESPNews",
                    "url": "https://thetvapp.to/tv/espnews-live-stream/",
                    "image": "https://the-tv.app/favicon.ico",
                    "isHost": true
                },
                {
                    "name": "TV | ESPNU",
                    "url": "https://thetvapp.to/tv/espnu-live-stream/",
                    "image": "https://the-tv.app/favicon.ico",
                    "isHost": true
                },
                {
                    "name": "TV | Food Network",
                    "url": "https://thetvapp.to/tv/food-network-live-stream/",
                    "image": "https://the-tv.app/favicon.ico",
                    "isHost": true
                },
                {
                    "name": "TV | Fox Business Network",
                    "url": "https://thetvapp.to/tv/fox-business-network-live-stream/",
                    "image": "https://the-tv.app/favicon.ico",
                    "isHost": true
                },
                {
                    "name": "TV | FOX News Channel",
                    "url": "https://thetvapp.to/tv/fox-news-channel-live-stream/",
                    "image": "https://the-tv.app/favicon.ico",
                    "isHost": true
                },
                {
                    "name": "TV | FOX Sports 1",
                    "url": "https://thetvapp.to/tv/fox-sports-1-live-stream/",
                    "image": "https://the-tv.app/favicon.ico",
                    "isHost": true
                },
                {
                    "name": "TV | FOX Sports 2",
                    "url": "https://thetvapp.to/tv/fox-sports-2-live-stream/",
                    "image": "https://the-tv.app/favicon.ico",
                    "isHost": true
                },
                {
                    "name": "TV | Freeform",
                    "url": "https://thetvapp.to/tv/freeform-live-stream/",
                    "image": "https://the-tv.app/favicon.ico",
                    "isHost": true
                },
                {
                    "name": "TV | Fuse HD",
                    "url": "https://thetvapp.to/tv/fuse-hd-live-stream/",
                    "image": "https://the-tv.app/favicon.ico",
                    "isHost": true
                },
                {
                    "name": "TV | FX Movie",
                    "url": "https://thetvapp.to/tv/fx-movie-live-stream/",
                    "image": "https://the-tv.app/favicon.ico",
                    "isHost": true
                },
                {
                    "name": "TV | Golf Channel",
                    "url": "https://thetvapp.to/tv/golf-channel-live-stream/",
                    "image": "https://the-tv.app/favicon.ico",
                    "isHost": true
                },
                {
                    "name": "TV | Hallmark",
                    "url": "https://thetvapp.to/tv/hallmark-live-stream/",
                    "image": "https://the-tv.app/favicon.ico",
                    "isHost": true
                },
                {
                    "name": "TV | Hallmark Drama HD",
                    "url": "https://thetvapp.to/tv/hallmark-drama-hd-live-stream/",
                    "image": "https://the-tv.app/favicon.ico",
                    "isHost": true
                },
                {
                    "name": "TV | Hallmark Movies & Mysteries HD",
                    "url": "https://thetvapp.to/tv/hallmark-movies-mysteries-hd-live-stream/",
                    "image": "https://the-tv.app/favicon.ico",
                    "isHost": true
                },
                {
                    "name": "TV | HBO 2 East",
                    "url": "https://thetvapp.to/tv/hbo-2-east-live-stream/",
                    "image": "https://the-tv.app/favicon.ico",
                    "isHost": true
                },
                {
                    "name": "TV | HBO Comedy HD",
                    "url": "https://thetvapp.to/tv/hbo-comedy-hd-live-stream/",
                    "image": "https://the-tv.app/favicon.ico",
                    "isHost": true
                },
                {
                    "name": "TV | HBO East",
                    "url": "https://thetvapp.to/tv/hbo-east-live-stream/",
                    "image": "https://the-tv.app/favicon.ico",
                    "isHost": true
                },
                {
                    "name": "TV | HBO Family East",
                    "url": "https://thetvapp.to/tv/hbo-family-east-live-stream/",
                    "image": "https://the-tv.app/favicon.ico",
                    "isHost": true
                },
                {
                    "name": "TV | HBO Signature",
                    "url": "https://thetvapp.to/tv/hbo-signature-live-stream/",
                    "image": "https://the-tv.app/favicon.ico",
                    "isHost": true
                },
                {
                    "name": "TV | HBO Zone HD",
                    "url": "https://thetvapp.to/tv/hbo-zone-hd-live-stream/",
                    "image": "https://the-tv.app/favicon.ico",
                    "isHost": true
                },
                {
                    "name": "TV | HGTV",
                    "url": "https://thetvapp.to/tv/hgtv-live-stream/",
                    "image": "https://the-tv.app/favicon.ico",
                    "isHost": true
                },
                {
                    "name": "TV | History",
                    "url": "https://thetvapp.to/tv/history-live-stream/",
                    "image": "https://the-tv.app/favicon.ico",
                    "isHost": true
                },
                {
                    "name": "TV | Investigation Discovery",
                    "url": "https://thetvapp.to/tv/investigation-discovery-live-stream/",
                    "image": "https://the-tv.app/favicon.ico",
                    "isHost": true
                },
                {
                    "name": "TV | ION Television East HD",
                    "url": "https://thetvapp.to/tv/ion-television-east-hd-live-stream/",
                    "image": "https://the-tv.app/favicon.ico",
                    "isHost": true
                },
                {
                    "name": "TV | Lifetime",
                    "url": "https://thetvapp.to/tv/lifetime-live-stream/",
                    "image": "https://the-tv.app/favicon.ico",
                    "isHost": true
                },
                {
                    "name": "TV | Logo",
                    "url": "https://thetvapp.to/tv/logo-live-stream/",
                    "image": "https://the-tv.app/favicon.ico",
                    "isHost": true
                },
                {
                    "name": "TV | MeTV Toons",
                    "url": "https://thetvapp.to/tv/metv-toons-live-stream/",
                    "image": "https://the-tv.app/favicon.ico",
                    "isHost": true
                },
                {
                    "name": "TV | MLB Network",
                    "url": "https://thetvapp.to/tv/mlb-network-live-stream/",
                    "image": "https://the-tv.app/favicon.ico",
                    "isHost": true
                },
                {
                    "name": "TV | MoreMAX",
                    "url": "https://thetvapp.to/tv/moremax-live-stream/",
                    "image": "https://the-tv.app/favicon.ico",
                    "isHost": true
                },
                {
                    "name": "TV | MotorTrend HD",
                    "url": "https://thetvapp.to/tv/motortrend-hd-live-stream/",
                    "image": "https://the-tv.app/favicon.ico",
                    "isHost": true
                },
                {
                    "name": "TV | MovieMAX",
                    "url": "https://thetvapp.to/tv/moviemax-live-stream/",
                    "image": "https://the-tv.app/favicon.ico",
                    "isHost": true
                },
                {
                    "name": "TV | MSNBC",
                    "url": "https://thetvapp.to/tv/msnbc-live-stream/",
                    "image": "https://the-tv.app/favicon.ico",
                    "isHost": true
                },
                {
                    "name": "TV | Nat Geo WILD",
                    "url": "https://thetvapp.to/tv/nat-geo-wild-live-stream/",
                    "image": "https://the-tv.app/favicon.ico",
                    "isHost": true
                },
                {
                    "name": "TV | National Geographic",
                    "url": "https://thetvapp.to/tv/national-geographic-live-stream/",
                    "image": "https://the-tv.app/favicon.ico",
                    "isHost": true
                },
                {
                    "name": "TV | NBA TV",
                    "url": "https://thetvapp.to/tv/nba-tv-live-stream/",
                    "image": "https://the-tv.app/favicon.ico",
                    "isHost": true
                },
                {
                    "name": "TV | Newsmax TV",
                    "url": "https://thetvapp.to/tv/newsmax-tv/",
                    "image": "https://the-tv.app/favicon.ico",
                    "isHost": true
                },
                {
                    "name": "TV | NFL Network",
                    "url": "https://thetvapp.to/tv/nfl-network-live-stream/",
                    "image": "https://the-tv.app/favicon.ico",
                    "isHost": true
                },
                {
                    "name": "TV | NFL Red Zone",
                    "url": "https://thetvapp.to/tv/nfl-red-zone/",
                    "image": "https://the-tv.app/favicon.ico",
                    "isHost": true
                },
                {
                    "name": "TV | NHL Network",
                    "url": "https://thetvapp.to/tv/nhl-network-live-stream/",
                    "image": "https://the-tv.app/favicon.ico",
                    "isHost": true
                },
                {
                    "name": "TV | Nick Jr.",
                    "url": "https://thetvapp.to/tv/nick-jr-live-stream/",
                    "image": "https://the-tv.app/favicon.ico",
                    "isHost": true
                },
                {
                    "name": "TV | Nickelodeon East",
                    "url": "https://thetvapp.to/tv/nickelodeon-east-live-stream/",
                    "image": "https://the-tv.app/favicon.ico",
                    "isHost": true
                },
                {
                    "name": "TV | Nicktoons",
                    "url": "https://thetvapp.to/tv/nicktoons-live-stream/",
                    "image": "https://the-tv.app/favicon.ico",
                    "isHost": true
                },
                {
                    "name": "TV | Outdoor Channel",
                    "url": "https://thetvapp.to/tv/outdoor-channel-live-stream/",
                    "image": "https://the-tv.app/favicon.ico",
                    "isHost": true
                },
                {
                    "name": "TV | Oxygen True Crime",
                    "url": "https://thetvapp.to/tv/oxygen-true-crime-live-stream/",
                    "image": "https://the-tv.app/favicon.ico",
                    "isHost": true
                },
                {
                    "name": "TV | PBS 13 (WNET) New York",
                    "url": "https://thetvapp.to/tv/pbs-13-wnet-new-york-live-stream/",
                    "image": "https://the-tv.app/favicon.ico",
                    "isHost": true
                },
                {
                    "name": "TV | ReelzChannel",
                    "url": "https://thetvapp.to/tv/reelzchannel-live-stream/",
                    "image": "https://the-tv.app/favicon.ico",
                    "isHost": true
                },
                {
                    "name": "TV | Science",
                    "url": "https://thetvapp.to/tv/science-live-stream/",
                    "image": "https://the-tv.app/favicon.ico",
                    "isHost": true
                },
                {
                    "name": "TV | SEC Network",
                    "url": "https://thetvapp.to/tv/sec-network-live-stream/",
                    "image": "https://the-tv.app/favicon.ico",
                    "isHost": true
                },
                {
                    "name": "TV | Showtime (E)",
                    "url": "https://thetvapp.to/tv/showtime-e-live-stream/",
                    "image": "https://the-tv.app/favicon.ico",
                    "isHost": true
                },
                {
                    "name": "TV | SHOWTIME 2",
                    "url": "https://thetvapp.to/tv/showtime-2-live-stream/",
                    "image": "https://the-tv.app/favicon.ico",
                    "isHost": true
                },
                {
                    "name": "TV | STARZ East",
                    "url": "https://thetvapp.to/tv/starz-east-live-stream/",
                    "image": "https://the-tv.app/favicon.ico",
                    "isHost": true
                },
                {
                    "name": "TV | SundanceTV HD",
                    "url": "https://thetvapp.to/tv/sundancetv-hd-live-stream/",
                    "image": "https://the-tv.app/favicon.ico",
                    "isHost": true
                },
                {
                    "name": "TV | SYFY",
                    "url": "https://thetvapp.to/tv/syfy-live-stream/",
                    "image": "https://the-tv.app/favicon.ico",
                    "isHost": true
                },
                {
                    "name": "TV | TeenNick",
                    "url": "https://thetvapp.to/tv/teennick-live-stream/",
                    "image": "https://the-tv.app/favicon.ico",
                    "isHost": true
                },
                {
                    "name": "TV | Telemundo East",
                    "url": "https://thetvapp.to/tv/telemundo-east-live-stream/",
                    "image": "https://the-tv.app/favicon.ico",
                    "isHost": true
                },
                {
                    "name": "TV | Tennis Channel",
                    "url": "https://thetvapp.to/tv/tennis-channel-live-stream/",
                    "image": "https://the-tv.app/favicon.ico",
                    "isHost": true
                },
                {
                    "name": "TV | The CW (WPIX New York)",
                    "url": "https://thetvapp.to/tv/the-cw-live-stream/",
                    "image": "https://the-tv.app/favicon.ico",
                    "isHost": true
                },
                {
                    "name": "TV | The Movie Channel East",
                    "url": "https://thetvapp.to/tv/the-movie-channel-east-live-stream/",
                    "image": "https://the-tv.app/favicon.ico",
                    "isHost": true
                },
                {
                    "name": "TV | The Weather Channel",
                    "url": "https://thetvapp.to/tv/the-weather-channel-live-stream/",
                    "image": "https://the-tv.app/favicon.ico",
                    "isHost": true
                },
                {
                    "name": "TV | Travel Channel",
                    "url": "https://thetvapp.to/tv/travel-channel-live-stream/",
                    "image": "https://the-tv.app/favicon.ico",
                    "isHost": true
                },
                {
                    "name": "TV | truTV",
                    "url": "https://thetvapp.to/tv/trutv-live-stream/",
                    "image": "https://the-tv.app/favicon.ico",
                    "isHost": true
                },
                {
                    "name": "TV | TV One HD",
                    "url": "https://thetvapp.to/tv/tv-one-hd-live-stream/",
                    "image": "https://the-tv.app/favicon.ico",
                    "isHost": true
                },
                {
                    "name": "TV | Universal Kids",
                    "url": "https://thetvapp.to/tv/universal-kids-live-stream/",
                    "image": "https://the-tv.app/favicon.ico",
                    "isHost": true
                },
                {
                    "name": "TV | Univision East",
                    "url": "https://thetvapp.to/tv/univision-east-live-stream/",
                    "image": "https://the-tv.app/favicon.ico",
                    "isHost": true
                },
                {
                    "name": "TV | USA Network",
                    "url": "https://thetvapp.to/tv/usa-network-live-stream/",
                    "image": "https://the-tv.app/favicon.ico",
                    "isHost": true
                },
                {
                    "name": "TV | VICE",
                    "url": "https://thetvapp.to/tv/vice-live-stream/",
                    "image": "https://the-tv.app/favicon.ico",
                    "isHost": true
                },
                {
                    "name": "TV | WABC (New York) ABC East",
                    "url": "https://thetvapp.to/tv/wabc-new-york-abc-east-live-stream/",
                    "image": "https://the-tv.app/favicon.ico",
                    "isHost": true
                },
                {
                    "name": "TV | WCBS (New York) CBS East",
                    "url": "https://thetvapp.to/tv/wcbs-new-york-cbs-east-live-stream/",
                    "image": "https://the-tv.app/favicon.ico",
                    "isHost": true
                },
                {
                    "name": "TV | WE tv",
                    "url": "https://thetvapp.to/tv/we-tv-live-stream/",
                    "image": "https://the-tv.app/favicon.ico",
                    "isHost": true
                },
                {
                    "name": "TV | WNBC (New York) NBC East",
                    "url": "https://thetvapp.to/tv/wnbc-new-york-nbc-east-live-stream/",
                    "image": "https://the-tv.app/favicon.ico",
                    "isHost": true
                },
                {
                    "name": "TV | WNYW (New York) FOX East",
                    "url": "https://thetvapp.to/tv/wnyw-new-york-fox-east-live-stream/",
                    "image": "https://the-tv.app/favicon.ico",
                    "isHost": true
                }
            ]
        }
    ]
}